tsfile/__init__.py
tsfile/libtsfile.so.2.1.4
tsfile/tsfile_py_cpp.cpython-39-x86_64-linux-gnu.so
tsfile/tablet.py
tsfile/tsfile_reader.cpython-39-x86_64-linux-gnu.so
tsfile/__init__.pxd
tsfile/tsfile_cpp.pxd
tsfile/utils.py
tsfile/libtsfile.so
tsfile/field.py
tsfile/row_record.py
tsfile/exceptions.py
tsfile/date_utils.py
tsfile/schema.py
tsfile/constants.py
tsfile/tsfile_py_cpp.pxd
tsfile/tsfile_writer.cpython-39-x86_64-linux-gnu.so
tsfile/tsfile_table_writer.py
tsfile/include/writer/tsfile_table_writer.h
tsfile/include/writer/time_page_writer.h
tsfile/include/writer/page_writer.h
tsfile/include/writer/chunk_writer.h
tsfile/include/writer/value_chunk_writer.h
tsfile/include/writer/time_chunk_writer.h
tsfile/include/writer/value_page_writer.h
tsfile/include/writer/tsfile_writer.h
tsfile/include/reader/bloom_filter.h
tsfile/include/reader/imeta_data_querier.h
tsfile/include/reader/device_meta_iterator.h
tsfile/include/reader/meta_data_querier.h
tsfile/include/reader/aligned_chunk_reader.h
tsfile/include/reader/result_set.h
tsfile/include/reader/table_result_set.h
tsfile/include/reader/tsfile_reader.h
tsfile/include/reader/chunk_reader.h
tsfile/include/reader/ichunk_reader.h
tsfile/include/reader/tsfile_series_scan_iterator.h
tsfile/include/reader/query_executor.h
tsfile/include/reader/column_mapping.h
tsfile/include/reader/tsfile_executor.h
tsfile/include/reader/table_query_executor.h
tsfile/include/reader/qds_with_timegenerator.h
tsfile/include/reader/scan_iterator.h
tsfile/include/reader/qds_without_timegenerator.h
tsfile/include/reader/expression.h
tsfile/include/reader/filter/not_eq.h
tsfile/include/reader/filter/lt.h
tsfile/include/reader/filter/lt_eq.h
tsfile/include/reader/filter/filter.h
tsfile/include/reader/filter/time_operator.h
tsfile/include/reader/filter/and_filter.h
tsfile/include/reader/filter/between.h
tsfile/include/reader/filter/filter_type.h
tsfile/include/reader/filter/eq.h
tsfile-2.1.4.dist-info/top_level.txt
tsfile-2.1.4.dist-info/WHEEL
tsfile-2.1.4.dist-info/RECORD
tsfile-2.1.4.dist-info/METADATA
