Metadata-Version: 2.4
Name: tsfile
Version: 2.1.4
Summary: TsFile Python
Maintainer-email: Apache TsFile Developers <dev@tsfile.apache.org>
Project-URL: Homepage, https://tsfile.apache.org/
Project-URL: Documentation, https://tsfile.apache.org/zh/UserGuide/latest/QuickStart/Navigating_Time_Series_Data.html
Project-URL: Repository, https://github.com/apache/tsfile
Project-URL: Issues, https://github.com/apache/tsfile/issues
Requires-Python: >=3.9
Requires-Dist: numpy>=1.20
Requires-Dist: pandas>=2.0
